rtgui/__init__.py
rtgui/communication/__init__.py
rtgui-0.0.5.dist-info/LICENSE
rtgui-0.0.5.dist-info/METADATA
rtgui-0.0.5.dist-info/WHEEL
rtgui-0.0.5.dist-info/top_level.txt
rtgui-0.0.5.dist-info/RECORD
